velopack-0.0.1369.dev7516.dist-info/METADATA
velopack-0.0.1369.dev7516.dist-info/WHEEL
velopack/__init__.py
velopack/velopack.abi3.so
velopack-0.0.1369.dev7516.dist-info/RECORD
