Metadata-Version: 2.4
Name: velopack
Version: 0.0.1369.dev7516
Summary: Installer and automatic update framework for cross-platform desktop applications
Home-Page: https://velopack.io
Author: Velopack Ltd, Caelan Sayler <git@caesay.com>
Author-email: Velopack Ltd, Caelan Sayler <git@caesay.com>
License: MIT
Requires-Python: >=3.8
